Workbook

Sheet Risk Register
A1: Status | B1: ID # | C1: Title | D1: Category | E1: Description | F1: Probability | G1: Impact | H1: Severity | I1: Owner | J1: Response Strategy
A2: Active | B2: 1 | C2: Security vulnerabities | D2: Technical | E2: Weak security that exposes the project and company to cyberthreats like data breaches and ransomware attacks | F2: High (4) | G2: Catastrophic (5) | H2: EXTREME | I2: Chief Security Officer (CSO) | J2: Establish security as a major priority, as project success is impossible without it. Design and enforce security protocols
A3: Active | B3: 2 | C3: Poor architechtural planning | D3: Technical | E3: The architecture of the project was not properly planned out so the project becomes inefficient, prone to failure, and hard to implement | F3: Low (2) | G3: Major (4) | H3: MEDIUM | I3: Project Design Lead | J3: Properly understand the project scope in order to carefully design the architecture of the different systems
A4: Active | B4: 3 | C4: Inter-system integration issues | D4: Technical | E4: The linking of multiple different platforms is challenging and can cause delays or slow work down | F4: Moderate (3) | G4: Moderate (3) | H4: MEDIUM | I4: Technical Project Leader | J4: Design with the intention of system interconnectedness, but keep the components loosely coupled
A5: Active | B5: 4 | C5: Inaccurate timeline estimates | D5: Schedule | E5: The project timeline was built on guesses rather than past data and experiences, so the estimated timeline will be difficult to fulfill due to difference in the planned and actual timelines | F5: Low (2) | G5: Moderate (3) | H5: MEDIUM | I5: Project Mananger (PM) | J5: Gather feedback from the development teams that will be working on the deliverables and incoroporate their estimates into the timeline
A6: Active | B6: 5 | C6: Inadequate delay buffers | D6: Schedule | E6: Not enough time was given inbetween tasks to allow a cushion for delays or undershot timeline estimates | F6: Moderate (3) | G6: Minor (2) | H6: MEDIUM | I6: Project Mananger (PM) | J6: Gather feedback from the development teams that will be working on the deliverables and add buffers at each milestone
A7: Active | B7: 6 | C7: Bottlenecks | D7: Schedule | E7: A workflow that other flows are dependent on the completion of before they can begin is stalled or stopped all together, slowing project progress in more than one area | F7: Moderate (3) | G7: Moderate (3) | H7: MEDIUM | I7: Project Mananger (PM) | J7: Visualize the workflow with a Kanban board (Trello). Identify critical path dependencies. Assign and leverage resource where necessary
A8: Active | B8: 7 | C8: Budget cuts | D8: Financial | E8: Loss of funding for the project | F8: Low (2) | G8: Major (4) | H8: MEDIUM | I8: Project Sponsor | J8: Define project scope to establish a backup plan to move needed funds from the "Nice-to-haves" to the "Must-haves". Draft a MoSCoW-style requirements list
A9: Active | B9: 8 | C9: Poor team communication | D9: People | E9: Teams are unable to properly exchange information in order to complete their work, both within and outside of their teams | F9: Low (2) | G9: Minor (2) | H9: LOW | I9: Project Mananger (PM) | J9: Have a universal communication method. Establish efficient documentation protocols
A10: Active | B10: 9 | C10: Team members skill gaps | D10: People | E10: Team members do not possess the necessary skills to complete their tasks, so work quality is not adequate and the timeline is delayed | F10: Low (2) | G10: Minor (2) | H10: LOW | I10: Project Mananger (PM) | J10: Have team leads assign roles and tasks based on team members' specialized skills. Pair junior members with senior mentors
A11: Active | B11: 10 | C11: Inadequate stakeholder engagement | D11: People | E11: Stakeholders are not fully engaged, so decisions regarding the course of the project | F11: Moderate (3) | G11: Moderate (3) | H11: MEDIUM | I11: Project Mananger (PM) | J11: Record weekly stakeholder update videos. Listen to feedback and take action based off it

Sheet Roles and Resources
A1: Roles | B1: Name | C1: FTE % | D1: Estimated Hours | E1: Hourly Rate | F1: Cost
A2: Project Manager | B2: Tony | C2: 0.5 | D2: 240 | E2: 100 | F2: =Table1[[#This Row],[Estimated Hours]]*Table1[[#This Row],[Hourly Rate]] -> 24000
A3: Lead System Archeitect | B3: Casey | C3: 1 | D3: 480 | E3: 180 | F3: =Table1[[#This Row],[Estimated Hours]]*Table1[[#This Row],[Hourly Rate]] -> 86400 | G3: Management and Architecture Subtotal: | H3: =SUM(F2:F3) -> 110400
A4: Lead Mobile Developer | B4: Kevin | C4: 1 | D4: 480 | E4: 150 | F4: =Table1[[#This Row],[Estimated Hours]]*Table1[[#This Row],[Hourly Rate]] -> 72000
A5: Senior Mobile Developer | B5: Tyler | C5: 1 | D5: 480 | E5: 110 | F5: =Table1[[#This Row],[Estimated Hours]]*Table1[[#This Row],[Hourly Rate]] -> 52800
A6: Senior Mobile Developer | B6: Amy | C6: 1 | D6: 480 | E6: 110 | F6: =Table1[[#This Row],[Estimated Hours]]*Table1[[#This Row],[Hourly Rate]] -> 52800
A7: Mobile Developer | B7: Sophia | C7: 1 | D7: 480 | E7: 80 | F7: =Table1[[#This Row],[Estimated Hours]]*Table1[[#This Row],[Hourly Rate]] -> 38400
A8: Mobile Developer | B8: Hui | C8: 1 | D8: 480 | E8: 80 | F8: =Table1[[#This Row],[Estimated Hours]]*Table1[[#This Row],[Hourly Rate]] -> 38400 | G8: Mobile Team Subtotal: | H8: =SUM(F4:F8) -> 254400
A9: Lead Web Developer | B9: Nico | C9: 1 | D9: 480 | E9: 140 | F9: =Table1[[#This Row],[Estimated Hours]]*Table1[[#This Row],[Hourly Rate]] -> 67200
A10: Senior Frontend Developer | B10: Irianna | C10: 1 | D10: 480 | E10: 115 | F10: =Table1[[#This Row],[Estimated Hours]]*Table1[[#This Row],[Hourly Rate]] -> 55200
A11: Senior UI/UX Lead | B11: Evelyn | C11: 1 | D11: 480 | E11: 115 | F11: =Table1[[#This Row],[Estimated Hours]]*Table1[[#This Row],[Hourly Rate]] -> 55200
A12: Frontend Developer | B12: Tyrone | C12: 1 | D12: 480 | E12: 85 | F12: =Table1[[#This Row],[Estimated Hours]]*Table1[[#This Row],[Hourly Rate]] -> 40800
A13: UI/UX Developer | B13: Mikaela | C13: 1 | D13: 480 | E13: 85 | F13: =Table1[[#This Row],[Estimated Hours]]*Table1[[#This Row],[Hourly Rate]] -> 40800 | G13: Web Team Subtotal: | H13: =SUM(F9:F13) -> 259200
A14: Full-Stack Developer (Flexible Assignment) | B14: Jeffrey | C14: 1 | D14: 480 | E14: 130 | F14: =Table1[[#This Row],[Estimated Hours]]*Table1[[#This Row],[Hourly Rate]] -> 62400 | G14: Full-Stack Subtotal: | H14: =SUM(Table1[[#This Row],[Cost]]) -> 62400
A15: Backend Lead Developer | B15: Sophie | C15: 1 | D15: 480 | E15: 150 | F15: =Table1[[#This Row],[Estimated Hours]]*Table1[[#This Row],[Hourly Rate]] -> 72000
A16: Senior Backend Developer | B16: Lando | C16: 1 | D16: 480 | E16: 120 | F16: =Table1[[#This Row],[Estimated Hours]]*Table1[[#This Row],[Hourly Rate]] -> 57600
A17: Backend Developer | B17: Franklin | C17: 1 | D17: 480 | E17: 90 | F17: =Table1[[#This Row],[Estimated Hours]]*Table1[[#This Row],[Hourly Rate]] -> 43200
A18: Database Administrator | B18: Leon | C18: 1 | D18: 480 | E18: 125 | F18: =Table1[[#This Row],[Estimated Hours]]*Table1[[#This Row],[Hourly Rate]] -> 60000
A19: Cloud Infrastructure Engineer | B19: Taylor | C19: 1 | D19: 480 | E19: 150 | F19: =Table1[[#This Row],[Estimated Hours]]*Table1[[#This Row],[Hourly Rate]] -> 72000 | G19: Backend Team Subtotal: | H19: =SUM(F15:F19) -> 304800
A20: Geographic Information System Integration Lead | B20: Kim | C20: 1 | D20: 480 | E20: 145 | F20: =Table1[[#This Row],[Estimated Hours]]*Table1[[#This Row],[Hourly Rate]] -> 69600
A21: Geographic Information System Analyst | B21: Cody | C21: 1 | D21: 480 | E21: 100 | F21: =Table1[[#This Row],[Estimated Hours]]*Table1[[#This Row],[Hourly Rate]] -> 48000
A22: Geographic Information System Technician | B22: Carlos | C22: 1 | D22: 480 | E22: 70 | F22: =Table1[[#This Row],[Estimated Hours]]*Table1[[#This Row],[Hourly Rate]] -> 33600
A23: Spatial Data Engineer | B23: Luca | C23: 1 | D23: 480 | E23: 130 | F23: =Table1[[#This Row],[Estimated Hours]]*Table1[[#This Row],[Hourly Rate]] -> 62400
A24: Cartographer | B24: Sergei | C24: 1 | D24: 480 | E24: 80 | F24: =Table1[[#This Row],[Estimated Hours]]*Table1[[#This Row],[Hourly Rate]] -> 38400 | G24: Mapping and Location Services Team Subtotal: | H24: =SUM(F20:F24) -> 252000
A25: Head of Payments (Payments Team Lead) | B25: Caitlyn | C25: 1 | D25: 480 | E25: 185 | F25: =Table1[[#This Row],[Estimated Hours]]*Table1[[#This Row],[Hourly Rate]] -> 88800
A26: Payments Security Engineer | B26: Violet | C26: 1 | D26: 480 | E26: 170 | F26: =Table1[[#This Row],[Estimated Hours]]*Table1[[#This Row],[Hourly Rate]] -> 81600
A27: Payments Intergration Engineer | B27: Jose | C27: 1 | D27: 480 | E27: 85 | F27: =Table1[[#This Row],[Estimated Hours]]*Table1[[#This Row],[Hourly Rate]] -> 40800
A28: Payments Operations Specialist | B28: Nathan | C28: 1 | D28: 480 | E28: 85 | F28: =Table1[[#This Row],[Estimated Hours]]*Table1[[#This Row],[Hourly Rate]] -> 40800
A29: Fraud and Risk Manager | B29: Marcus | C29: 1 | D29: 480 | E29: 160 | F29: =Table1[[#This Row],[Estimated Hours]]*Table1[[#This Row],[Hourly Rate]] -> 76800 | G29: Payment Team Subtotal: | H29: =SUM(F25:F29) -> 328800
A30: QA Lead | B30: Nicole | C30: 1 | D30: 480 | E30: 110 | F30: =Table1[[#This Row],[Estimated Hours]]*Table1[[#This Row],[Hourly Rate]] -> 52800
A31: QA Test Manager | B31: Thomas | C31: 1 | D31: 480 | E31: 120 | F31: =Table1[[#This Row],[Estimated Hours]]*Table1[[#This Row],[Hourly Rate]] -> 57600
A32: QA Engineer | B32: Benny | C32: 1 | D32: 480 | E32: 80 | F32: =Table1[[#This Row],[Estimated Hours]]*Table1[[#This Row],[Hourly Rate]] -> 38400
A33: QA Test Analyst | B33: Silvio | C33: 1 | D33: 480 | E33: 75 | F33: =Table1[[#This Row],[Estimated Hours]]*Table1[[#This Row],[Hourly Rate]] -> 36000
A34: QA Tester | B34: Franchesca | C34: 1 | D34: 480 | E34: 55 | F34: =Table1[[#This Row],[Estimated Hours]]*Table1[[#This Row],[Hourly Rate]] -> 26400
A35: QA Tester | B35: Colin | C35: 1 | D35: 480 | E35: 55 | F35: =Table1[[#This Row],[Estimated Hours]]*Table1[[#This Row],[Hourly Rate]] -> 26400 | G35: QA and Testing Team Subtotal: | H35: =SUM(F30:F35) -> 237600
A36: Total | F36: =SUM(Table1[Cost]) -> 1809600 | H36: =SUM(H3, H8, H13, H14, H19, H24, H29, H35) -> 1809600

Sheet Resource and Cost Plan
A1: Item | B1: Category | C1: Quantity/Months | D1: Unit Cost | E1: Duration (Months) | F1: Total | G1: Notes
A2: Management and Architecture Pay | B2: Labor | C2: 240 | D2: =Table2[[#This Row],[Total]]/Table2[[#This Row],[Quantity/Months]] -> 460 | E2: 3 | F2: ='Roles and Resources'!H3 -> 110400
A3: Mobile Application Team Pay | B3: Labor | C3: 600 | D3: =Table2[[#This Row],[Total]]/Table2[[#This Row],[Quantity/Months]] -> 424 | E3: 3 | F3: ='Roles and Resources'!H8 -> 254400
A4: Web Application Team Pay | B4: Labor | C4: 600 | D4: =Table2[[#This Row],[Total]]/Table2[[#This Row],[Quantity/Months]] -> 432 | E4: 3 | F4: ='Roles and Resources'!H13 -> 259200
A5: Fullstack Team Pay | B5: Labor | C5: 160 | D5: =Table2[[#This Row],[Total]]/Table2[[#This Row],[Quantity/Months]] -> 390 | E5: 3 | F5: ='Roles and Resources'!H14 -> 62400
A6: Backend/API Team Pay | B6: Labor | C6: 600 | D6: =Table2[[#This Row],[Total]]/Table2[[#This Row],[Quantity/Months]] -> 508 | E6: 3 | F6: ='Roles and Resources'!H19 -> 304800
A7: Mapping & Location Services Team Pay | B7: Labor | C7: 600 | D7: =Table2[[#This Row],[Total]]/Table2[[#This Row],[Quantity/Months]] -> 420 | E7: 3 | F7: ='Roles and Resources'!H24 -> 252000
A8: Payment Integration Team | B8: Labor | C8: 600 | D8: =Table2[[#This Row],[Total]]/Table2[[#This Row],[Quantity/Months]] -> 548 | E8: 3 | F8: ='Roles and Resources'!H29 -> 328800
A9: Quality Assurance & and Testing Team | B9: Labor | C9: 720 | D9: =Table2[[#This Row],[Total]]/Table2[[#This Row],[Quantity/Months]] -> 330 | E9: 3 | F9: ='Roles and Resources'!H35 -> 237600
A10: Cloud Hosting | B10: Infrastructure | C10: 2000 | D10: 2000 | E10: 3 | F10: =Table2[[#This Row],[Unit Cost]]*Table2[[#This Row],[Duration (Months)]] -> 6000
A11: Licenses | B11: Tools | C11: 20000 | D11: 20000 | E11: 3 | F11: =Table2[[#This Row],[Unit Cost]]*Table2[[#This Row],[Duration (Months)]] -> 60000
A12: Third-Party APIs | B12: Tools | C12: 8000 | D12: 8000 | E12: 3 | F12: =Table2[[#This Row],[Unit Cost]]*Table2[[#This Row],[Duration (Months)]] -> 24000
A13: Contingency | B13: Reserver | C13: 0.1 | D13: Applied to Total | E13: N/A | F13: =SUM(F2:F12)*Table2[[#This Row],[Quantity/Months]] + SUM(F2:F12) -> 2089560

Sheet RACI Matrix
A1: Task/Role | B1: PM | C1: Architect | D1: Mobile Team | E1: Web Team | F1: Full-Stack | G1: Backend | H1: Mapping and Location Services | I1: Payment | J1: QA and Testing
A2: System Architecture Design | B2: A | C2: R | D2: C | E2: C | F2: C | G2: C | H2: C | I2: C | J2: I
A3: Cloud Hosting & Infrastructure Setup | B3: I | C3: A | D3: C | E3: I | F3: I | G3: R | H3: C | I3: C | J3: I
A4: UI/UX Design Wireframes | B4: A | C4: C | D4: I | E4: C | F4: R | G4: R | H4: I | I4: I | J4: I
A5: Mobile App Implementation | B5: A | C5: C | D5: I | E5: R | F5: C | G5: C | H5: I | I5: I | J5: I
A6: Web Frontend Implementation | B6: A | C6: C | D6: I | E6: C | F6: R | G6: R | H6: I | I6: I | J6: I
A7: Backend Service & API Development | B7: A | C7: C | D7: I | E7: C | F7: R | G7: R | H7: I | I7: I | J7: I
A8: GIS Mapping Integration | B8: A | C8: C | D8: I | E8: C | F8: C | G8: C | H8: R | I8: I | J8: I
A9: Payment Gateway Integration | B9: A | C9: C | D9: C | E9: C | F9: C | G9: C | H9: I | I9: R | J9: I
A10: Fraud & Risk Rules Definition | B10: I | C10: C | D10: A | E10: I | F10: R | G10: R | H10: I | I10: C | J10: I
A11: End-to-End QA Testing Cycles | B11: A | C11: I | D11: I | E11: C | F11: C | G11: C | H11: C | I11: C | J11: R
